Workbook

Sheet Dashboard
B5: COMPANY NAME
B10: Month-End Close Dashboard
B12: Version: | C12: v1.0
B13: Last Updated: | C13: 46059
B14: Owner: | C14: Armand Slabbert
B16: RAG | C16: Count | E16: Critical Tasks | F16: Count
B17: 🔴 Red | C17: =COUNTIF(Checklist!F3:F5000,"🔴 Red") -> 5 | E17: Critical Count | F17: =CONCATENATE(COUNTIF(Checklist!G3:G5000,"Yes")," Tasks") -> 14 Tasks
B18: 🟠 Amber | C18: =COUNTIF(Checklist!F3:F5000,"🟠 Amber") -> 6 | E18: Red & Critical | F18: =CONCATENATE(COUNTIFS(Checklist!G3:G5000,"Yes",Checklist!F3:F5000,"🔴 Red")," Tasks") -> 4 Tasks
B19: 🟡 Yellow | C19: =COUNTIF(Checklist!F3:F5000,"🟡 Yellow") -> 1 | E19: Amber & Critical | F19: =CONCATENATE(COUNTIFS(Checklist!G3:G5000,"Yes",Checklist!F3:F5000,"🟠 Amber")," Tasks") -> 5 Tasks
B20: 🟢 Green | C20: =COUNTIF(Checklist!F2:F4999,"🟢 Green") -> 8
C21: =SUM(C17:C20) -> 20
B23: RAG Legend
B24: Red = Not started / critical risk
B25: Amber = Queries
B26: Yellow = Work in progress / awaiting review
B27: Green = Finalised

Sheet Checklist
D1: Refer to tab Assumptions - EMPLOYEE | E1: Refer to tab Assumptions - STATUS
B2: Task Category | C2: Task Description | D2: Owner | E2: Status | F2: RAG | G2: Critical Tasks | H2: Due Date | I2: Completed Date | J2: Reviewed By | K2: Notes
B3: Pre-Close | C3: Confirm month-end close timetable | D3: Thabo Maseko | E3: Not Started | F3: =IFERROR(VLOOKUP(E3,Table4[[#All],[Status]:[RAG]],2,FALSE),"") -> 🔴 Red | G3: Yes | H3: 46055 | I3: 46081 | J3: Thabo Maseko | M3: =IFERROR(VLOOKUP(E3,'Assumptions - STATUS'!B2:B10,2,FALSE),"")
B4: Pre-Close | C4: Ensure all source documents received | D4: Annelie van Wyk | E4: Pending Input | F4: =IFERROR(VLOOKUP(E4,Table4[[#All],[Status]:[RAG]],2,FALSE),"") -> 🟠 Amber | G4: Yes | H4: 46055 | I4: 46081 | J4: Annelie van Wyk
B5: Cash & Banking | C5: Perform bank reconciliations | D5: Siphelele Dlamini | E5: Finalised | F5: =IFERROR(VLOOKUP(E5,Table4[[#All],[Status]:[RAG]],2,FALSE),"") -> 🟢 Green | G5: No | H5: 46055 | I5: 46081 | J5: Siphelele Dlamini
B6: Cash & Banking | C6: Review outstanding reconciling items | D6: Johan Botha | E6: Not Started | F6: =IFERROR(VLOOKUP(E6,Table4[[#All],[Status]:[RAG]],2,FALSE),"") -> 🔴 Red | G6: Yes | H6: 46055 | I6: 46081 | J6: Johan Botha
B7: Revenue | C7: Verify revenue completeness and cut-off | D7: Naledi Molefe | E7: Pending Input | F7: =IFERROR(VLOOKUP(E7,Table4[[#All],[Status]:[RAG]],2,FALSE),"") -> 🟠 Amber | G7: Yes | H7: 46055 | I7: 46081 | J7: Naledi Molefe
B8: Revenue | C8: Reconcile revenue to sub-ledgers | D8: Pieter du Plessis | E8: Finalised | F8: =IFERROR(VLOOKUP(E8,Table4[[#All],[Status]:[RAG]],2,FALSE),"") -> 🟢 Green | G8: Yes | H8: 46055 | I8: 46081 | J8: Pieter du Plessis
B9: Expenses | C9: Capture all supplier invoices | D9: Zandile Nkomo | E9: Not Started | F9: =IFERROR(VLOOKUP(E9,Table4[[#All],[Status]:[RAG]],2,FALSE),"") -> 🔴 Red | G9: Yes | H9: 46055 | I9: 46081 | J9: Zandile Nkomo
B10: Expenses | C10: Review accruals and prepayments | D10: Willem Pretorius | E10: In Progress | F10: =IFERROR(VLOOKUP(E10,Table4[[#All],[Status]:[RAG]],2,FALSE),"") -> 🟠 Amber | G10: No | H10: 46055 | I10: 46081 | J10: Willem Pretorius
B11: Payroll | C11: Reconcile payroll to general ledger | D11: Lerato Kgosi | E11: Finalised | F11: =IFERROR(VLOOKUP(E11,Table4[[#All],[Status]:[RAG]],2,FALSE),"") -> 🟢 Green | G11: Yes | H11: 46055 | I11: 46081 | J11: Lerato Kgosi
B12: Payroll | C12: Review payroll accruals | D12: Heinrich Müller | E12: Not Started | F12: =IFERROR(VLOOKUP(E12,Table4[[#All],[Status]:[RAG]],2,FALSE),"") -> 🔴 Red | G12: No | H12: 46055 | I12: 46081 | J12: Heinrich Müller
B13: Assets | C13: Review fixed asset register | D13: Busisiwe Zulu | E13: Prepared | F13: =IFERROR(VLOOKUP(E13,Table4[[#All],[Status]:[RAG]],2,FALSE),"") -> 🟡 Yellow | G13: Yes | H13: 46055 | I13: 46081 | J13: Busisiwe Zulu
B14: Assets | C14: Post depreciation journals | D14: Francois Joubert | E14: Finalised | F14: =IFERROR(VLOOKUP(E14,Table4[[#All],[Status]:[RAG]],2,FALSE),"") -> 🟢 Green | G14: Yes | H14: 46055 | I14: 46081 | J14: Francois Joubert
B15: Tax & VAT | C15: Prepare VAT reconciliation | D15: Kagiso Mokoena | E15: In Progress | F15: =IFERROR(VLOOKUP(E15,Table4[[#All],[Status]:[RAG]],2,FALSE),"") -> 🟠 Amber | G15: Yes | H15: 46055 | I15: 46081 | J15: Kagiso Mokoena
... B22: Review | C22: Final lock of accounting period | D22: Arno Steyn | E22: Finalised | F22: =IFERROR(VLOOKUP(E22,Table4[[#All],[Status]:[RAG]],2,FALSE),"") -> 🟢 Green | G22: No | H22: 46055 | I22: 46081 | J22: Arno Steyn

Sheet Assumptions - STATUS
A1: Status | B1: RAG | C1: Column1 | D1: Applies To | E1: Key Assumptions | F1: Control Requirement | G1: Evidence Required
A2: Not Started | B2: 🔴 Red | C2: No | D2: All close tasks | E2: Period still open; no workpapers or journals created | F2: No review or estimates permitted without approval | G2: None
A3: Pending Input | B3: 🟠 Amber | C3: Yes | D3: Tasks with external dependencies | E3: Required information identified and outstanding | F3: Follow-ups documented; estimates only if approved | G3: Email trail / request log
A4: In Progress | B4: 🟠 Amber | C4: No | D4: All operational close tasks | E4: All source data received; work actively underway | F4: Numbers provisional; not relied on for reporting | G4: Draft schedules / reconciliations
A5: Prepared | B5: 🟡 Yellow | C5: No | D5: All balance sheet reconciliations | E5: Reconciliation balances to GL; no unexplained differences | F5: Independent review required | G5: Signed reconciliation + GL extract
A6: Under Review | B6: 🟡 Yellow | C6: Yes | D6: All prepared close tasks | E6: Reviewer actively assessing accuracy and completeness | F6: No posting without reviewer approval | G6: Review notes / checklist
A7: Queries Raised | B7: 🟡 Yellow | C7: Yes | D7: Reviewed tasks with issues | E7: Issues identified and communicated to preparer | F7: All queries must be resolved before approval | G7: Query log / email correspondence
A8: Reworked / Updated | B8: 🟡 Yellow | C8: Yes | D8: Tasks returned after review | E8: All review queries addressed; schedules updated | F8: Must be re-reviewed before approval | G8: Updated reconciliation + adjustment journals
A9: Approved | B9: 🟢 Green | C9: No | D9: All close tasks | E9: Reviewer satisfied; no unresolved differences | F9: Numbers locked for reporting | G9: Reviewer sign-off
A10: Finalised | B10: 🟢 Green | C10: No | D10: Reporting and compliance outputs | E10: Included in management pack; period locked | F10: Changes require CFO approval | G10: Management pack / submission confirmation

Sheet Assumptions - EMPLOYEE
A1: Owner & Reviewer | B1: Job Title
A2: Thabo Maseko | B2: Chief Financial Officer
A3: Annelie van Wyk | B3: Finance Manager
A4: Siphelele Dlamini | B4: Senior Accountant
A5: Johan Botha | B5: Junior Accountant
A6: Naledi Molefe | B6: Bookkeeper
A7: Pieter du Plessis | B7: Creditors Clerk
A8: Zandile Nkomo | B8: Debtors Clerk
A9: Willem Pretorius | B9: Financial Controller
A10: Lerato Kgosi | B10: Management Accountant
A11: Heinrich Müller | B11: Group Reporting Accountant
A12: Busisiwe Zulu | B12: Payroll Administrator
... A23: Jacques le Roux | B23: Head of Finance Operations

Sheet Useful tips
B2: Accuracy & Risk Controls
B4: Source System – trace every number back to origin
B5: Amount / Exposure – supports value-based prioritisation
B6: Material? (Yes/No) – enables risk-based review
B7: Risk Rating (High/Medium/Low) – inherent risk vs execution status
B9: Review & Audit Evidence
B11: Reviewer Sign-off Date – proves independent review
B12: Journal Ref / Batch ID – end-to-end traceability
B13: Evidence Location – exact folder / link for audit speed
B15: Exception & Change Management
B17: Standard / Exception – explains deviations
B18: Post-Close Adjustment? – protects you during audits
... B25: Automation Level (Manual / Semi-Automated / Automated)
